coptpy/__init__.py
coptpy/copt_python.dll
coptpy/coptcore.pyd
coptpy/coptcore.pyi
coptpy/coptpywrap.pyd
coptpy/py.typed
coptpy-8.0.3.dist-info/METADATA
coptpy-8.0.3.dist-info/WHEEL
coptpy-8.0.3.dist-info/top_level.txt
coptpy-8.0.3.dist-info/RECORD
